ninja_mcp/__init__.py
ninja_mcp/server.py
ninja_mcp/testing.py
ninja_mcp/types.py
ninja_mcp/openapi/__init__.py
ninja_mcp/openapi/convert.py
ninja_mcp/openapi/utils.py
ninja_mcp/transport/__init__.py
ninja_mcp/transport/sse.py
django_ninja_mcp-0.0.1a2.dist-info/METADATA
django_ninja_mcp-0.0.1a2.dist-info/WHEEL
django_ninja_mcp-0.0.1a2.dist-info/licenses/LICENCE
django_ninja_mcp-0.0.1a2.dist-info/RECORD
