Metadata-Version: 2.4
Name: django-ninja-mcp
Version: 0.0.1a2
Summary: MCP extension for django-ninja
Project-URL: homepage, https://github.com/mikeedjones/django-ninja-mcp
Project-URL: documentation, https://github.com/mikeedjones/django-ninja-mcp
Project-URL: repository, https://github.com/mikeedjones/django-ninja-mcp
Author-email: Michael Jones <mike.ed.jones@gmail.com>
License-File: LICENCE
Requires-Python: >=3.10
Requires-Dist: daphne>=4.1.2
Requires-Dist: django-eventstream>=5.3.2
Requires-Dist: django-ninja>=1.4.1
Requires-Dist: mcp>=1.6.0
Requires-Dist: pydantic>=2.5.3
